LICENSE.md
MANIFEST.in
README.md
requirements.txt
setup.cfg
setup.py
version.txt
m2core/__init__.py
m2core/app_env.py
m2core/m2core.py
m2core.egg-info/PKG-INFO
m2core.egg-info/SOURCES.txt
m2core.egg-info/dependency_links.txt
m2core.egg-info/requires.txt
m2core.egg-info/top_level.txt
m2core/bases/__init__.py
m2core/bases/base_handler.py
m2core/bases/base_model.py
m2core/data_schemes/__init__.py
m2core/data_schemes/db_system_scheme.py
m2core/data_schemes/redis_system_scheme.py
m2core/db/__init__.py
m2core/db/sqlalchemy_json.py
m2core/utils/__init__.py
m2core/utils/data_helper.py
m2core/utils/decorators.py
m2core/utils/error.py
m2core/utils/json_helper.py
m2core/utils/permissions.py
m2core/utils/session_helper.py
m2core/utils/tests.py
m2core/utils/url_parser.py
m2core/utils/voluptuous_checkers.py
m2core/utils/sqlalchemy_mixins/__init__.py
m2core/utils/sqlalchemy_mixins/data_mixin.py
m2core/utils/sqlalchemy_mixins/deco_mixin.py
m2core/utils/sqlalchemy_mixins/decorators.py
m2core/utils/sqlalchemy_mixins/session_mixin.py