Metadata-Version: 1.1
Name: m2core
Version: 1.0.10
Summary: M2Core REST API web framework
Home-page: https://github.com/mdutkin/m2core
Author: Maxim Dutkin
Author-email: max@dutkin.ru
License: MIT License
Platform: UNKNOWN
Classifier: Environment :: Web Environment
Classifier: Intended Audience :: Developers
Classifier: License :: OSI Approved :: MIT License
Classifier: Operating System :: OS Independent
Classifier: Programming Language :: Python :: 3
Classifier: Topic :: Internet :: WWW/HTTP :: Dynamic Content
